logcenter_sdk/__init__.py
logcenter_sdk/client.py
logcenter_sdk/config.py
logcenter_sdk/exceptions.py
logcenter_sdk/middleware.py
logcenter_sdk/sender.py
logcenter_sdk/spool.py
logcenter_sdk-0.1.0.dev0.dist-info/LICENSE
logcenter_sdk-0.1.0.dev0.dist-info/METADATA
logcenter_sdk-0.1.0.dev0.dist-info/WHEEL
logcenter_sdk-0.1.0.dev0.dist-info/top_level.txt
logcenter_sdk-0.1.0.dev0.dist-info/RECORD
