Metadata-Version: 2.2
Name: logcenter-sdk
Version: 0.1.0.dev0
Summary: SDK oficial para envio de logs ao LogCenter
Author-email: DreamBricks <projetos@dreambricks.com.br>
License: MIT License
Project-URL: Homepage, https://github.com/dreambricks/logcenter_sdk
Classifier: Programming Language :: Python :: 3
Classifier: Operating System :: OS Independent
Requires-Python: >=3.9
License-File: LICENSE
Requires-Dist: httpx>=0.24.0
Requires-Dist: pydantic>=2.0.0
Requires-Dist: python-dotenv==1.1.1
